rubix_admin/__init__.py
rubix_admin/_version.py
rubix_admin/admin_config.py
rubix_admin/command_line.py
rubix_admin/daemon.py
rubix_admin/installer.py
rubix_admin/parsers.py
rubix_admin-0.4.0.dist-info/DESCRIPTION.rst
rubix_admin-0.4.0.dist-info/METADATA
rubix_admin-0.4.0.dist-info/RECORD
rubix_admin-0.4.0.dist-info/WHEEL
rubix_admin-0.4.0.dist-info/entry_points.txt
rubix_admin-0.4.0.dist-info/metadata.json
rubix_admin-0.4.0.dist-info/top_level.txt
