Metadata-Version: 2.0
Name: rubix-admin
Version: 0.4.0
Summary: Admin tool for Qubole Rubix
Home-page: https://github.com/qubole/rubix_admin.git
Author: Qubole
Author-email: dev@qubole.com
License: UNKNOWN
Platform: UNKNOWN
Requires-Dist: cryptography (==2.0.3)
Requires-Dist: argparse (>=1.3.0)
Requires-Dist: inflection (==0.3.1)
Requires-Dist: fabric (==1.13)
Requires-Dist: pycrypto (==2.6.1)
Requires-Dist: PyYaml (==3.12)
